Metadata-Version: 2.1
Name: accsetupparse
Version: 0.0.7
Summary: Library for converting and storing ACC json setups into Python class
Home-page: https://github.com/jura43/acc-setup-parse
Author: Jurica Slovinac
License: GPLv3
Project-URL: Home, https://github.com/jura43/acc-setup-parse
Project-URL: Changelog, https://github.com/jura43/acc-setup-parse/blob/master/README.md
Keywords: parser
License-File: LICENSE.md
